{
  "version": "7",
  "dialect": "postgresql",
  "entries": [
    {
      "idx": 0,
      "version": "7",
      "when": 1768842483750,
      "tag": "0000_cute_ultron",
      "breakpoints": true
    },
    {
      "idx": 1,
      "version": "7",
      "when": 1768845288606,
      "tag": "0001_magenta_valkyrie",
      "breakpoints": true
    },
    {
      "idx": 2,
      "version": "7",
      "when": 1768889033158,
      "tag": "0002_medical_steel_serpent",
      "breakpoints": true
    },
    {
      "idx": 3,
      "version": "7",
      "when": 1771084419329,
      "tag": "0003_cynical_vulcan",
      "breakpoints": true
    },
    {
      "idx": 4,
      "version": "7",
      "when": 1771135234267,
      "tag": "0004_outgoing_roulette",
      "breakpoints": true
    },
    {
      "idx": 5,
      "version": "7",
      "when": 1771136020413,
      "tag": "0005_next_doctor_doom",
      "breakpoints": true
    },
    {
      "idx": 6,
      "version": "7",
      "when": 1771136346008,
      "tag": "0006_absent_post",
      "breakpoints": true
    },
    {
      "idx": 7,
      "version": "7",
      "when": 1771137074896,
      "tag": "0007_bitter_steve_rogers",
      "breakpoints": true
    },
    {
      "idx": 8,
      "version": "7",
      "when": 1771137409369,
      "tag": "0008_conscious_chamber",
      "breakpoints": true
    },
    {
      "idx": 9,
      "version": "7",
      "when": 1771143886837,
      "tag": "0009_optimal_xorn",
      "breakpoints": true
    },
    {
      "idx": 10,
      "version": "7",
      "when": 1771144589922,
      "tag": "0010_serious_absorbing_man",
      "breakpoints": true
    },
    {
      "idx": 11,
      "version": "7",
      "when": 1771145560335,
      "tag": "0011_wandering_black_crow",
      "breakpoints": true
    },
    {
      "idx": 12,
      "version": "7",
      "when": 1771163489165,
      "tag": "0012_rapid_agent_zero",
      "breakpoints": true
    },
    {
      "idx": 13,
      "version": "7",
      "when": 1771163974201,
      "tag": "0013_sudden_midnight",
      "breakpoints": true
    },
    {
      "idx": 14,
      "version": "7",
      "when": 1771164877633,
      "tag": "0014_demonic_blockbuster",
      "breakpoints": true
    },
    {
      "idx": 15,
      "version": "7",
      "when": 1771176141033,
      "tag": "0015_real_lizard",
      "breakpoints": true
    },
    {
      "idx": 16,
      "version": "7",
      "when": 1771408270087,
      "tag": "0016_mysterious_morg",
      "breakpoints": true
    }
  ]
}